pyfcopy/__init__.py
pyfcopy/copy.py
pyfcopy/copy_file.py
pyfcopy/dummy_progress.py
pyfcopy/index.py
pyfcopy/merge.py
pyfcopy/progress.py
pyfcopy/remove.py
pyfcopy-0.1.0.dist-info/LICENSE.md
pyfcopy-0.1.0.dist-info/WHEEL
pyfcopy-0.1.0.dist-info/METADATA
pyfcopy-0.1.0.dist-info/RECORD
