Metadata-Version: 2.1
Name: pyfcopy
Version: 0.1.0
Summary: Provides high-level functionality on the filesystem.
Home-page: https://github.com/arnegroskurth/pyfcopy
License: MIT
Keywords: File,Tree,Filesystem,Copy,Move
Author: Arne Groskurth
Author-email: arne.groskurth@gears9.de
Requires-Python: >=3.6,<4.0
Classifier: License :: OSI Approved :: MIT License
Classifier: Programming Language :: Python :: 3
Classifier: Programming Language :: Python :: 3.6
Classifier: Programming Language :: Python :: 3.7
Classifier: Programming Language :: Python :: 3.8
Project-URL: Documentation, https://github.com/arnegroskurth/pyfcopy/doc/
Project-URL: Repository, https://github.com/arnegroskurth/pyfcopy
Project-URL: issues, https://github.com/arnegroskurth/pyfcopy/issues
